Metadata-Version: 2.1
Name: mbpro
Version: 0.0.5
Summary: Faz tudo o que voce quiser
Home-page: https://t.me/mbpro_module
Author: Master Bank
Author-email: mbpro_python@gmail.com
License: MIT License
Keywords: mbpro expert
Platform: UNKNOWN
